tdavec/__init__.py
tdavec/tdavec_core.c
tdavec/tdavec_core.cpython-312-darwin.so
tdavec/tdavec_core.pyx
tdavec/unit_test.py
tdavec/vectorizer.py
tdavec-0.1.43.dist-info/licenses/LICENSE
tdavec-0.1.43.dist-info/METADATA
tdavec-0.1.43.dist-info/WHEEL
tdavec-0.1.43.dist-info/top_level.txt
tdavec-0.1.43.dist-info/RECORD
