Metadata-Version: 2.4
Name: tdavec
Version: 0.1.43
Requires-Python: >=3.12
License-File: LICENSE
Requires-Dist: numpy==1.26.4
Requires-Dist: ripser==0.6.8
Dynamic: license-file
